sniprag/__init__.py
sniprag/core/__init__.py
sniprag/core/base_engine.py
sniprag/core/engine.py
sniprag/core/ocr_engine.py
sniprag/core/semantic_engine.py
sniprag/utils/__init__.py
sniprag-0.2.0.dist-info/licenses/LICENSE
sniprag-0.2.0.dist-info/METADATA
sniprag-0.2.0.dist-info/WHEEL
sniprag-0.2.0.dist-info/top_level.txt
sniprag-0.2.0.dist-info/RECORD
